udata_front/__init__.py
udata_front/api.py
udata_front/forms.py
udata_front/models.py
udata_front/settings.py
udata_front/tasks.py
udata_front/frontend/__init__.py
udata_front/frontend/error_handlers.py
udata_front/frontend/helpers.py
udata_front/frontend/menu_helpers.py
udata_front/frontend/resource_helpers.py
udata_front/harvesters/__init__.py
udata_front/harvesters/maaf.py
udata_front/harvesters/maaf.xsd
udata_front/harvesters/tests.py
udata_front/migrations/2015-07-07-C3-datasets-titles.txt
udata_front/migrations/2015-07-10-dataconnexions-badges.js
udata_front/migrations/2015-09-14-dataconnexions-6.js
udata_front/migrations/2015-09-28-fix-maaf-harvester-doublouns.js
udata_front/migrations/2016-04-05-deactivate-datapublica.js
udata_front/migrations/2017-01-05-geozones-admin-levels-fr.js
udata_front/migrations/2017-08-04-fix-wrong-spatial-coverages.js
udata_front/migrations/2018-04-09-normalize-resource-filetype.js
udata_front/migrations/2018-04-18-migrate-active-users.js
udata_front/static/c3/logo-c3.png
udata_front/static/dataconnexions/dataconnexions6-logo-couleur.png
udata_front/static/dataconnexions/logo-blanc-rouge.png
udata_front/static/dataconnexions/logo-blanc.png
udata_front/static/dataconnexions/logo-couleur-rouge.png
udata_front/static/dataconnexions/logo-couleur.png
udata_front/static/dataconnexions/logo-transparent.png
udata_front/static/faq/integration/exemple-integration-blog-etalab.png
udata_front/static/faq/outils/800px-CartePOI.png
udata_front/static/faq/outils/800px-Evolutionbio.png
udata_front/static/faq/outils/800px-Inventaire_du_patrimoine_Poitou-Chatrentes.png
udata_front/static/faq/outils/800px-Inventaire_du_patrimoine_vecteurs.png
udata_front/static/faq/outils/800px-OSM-cadastre.png
udata_front/static/faq/outils/800px-TileMill.png
udata_front/static/faq/outils/Alluvial.png
udata_front/static/faq/outils/Dependencies.png
udata_front/static/faq/outils/Heatmap-salons-coiffure-paris-opendatasoft.png
udata_front/static/faq/outils/PAC2012.jpg
udata_front-4.0.2.dist-info/LICENSE
udata_front-4.0.2.dist-info/METADATA
udata_front-4.0.2.dist-info/WHEEL
udata_front-4.0.2.dist-info/entry_points.txt
udata_front-4.0.2.dist-info/top_level.txt
udata_front-4.0.2.dist-info/RECORD
