Metadata-Version: 2.1
Name: udata-front
Version: 4.0.2
Summary: udata customizations for data.gouv.fr
Home-page: https://github.com/datagouv/udata-front
Author: Etalab
Author-email: pypi@data.gouv.fr
License: LGPL
Keywords: udata opendata portal etalab
Classifier: Development Status :: 3 - Alpha
Classifier: Programming Language :: Python
Classifier: Environment :: Web Environment
Classifier: Operating System :: OS Independent
Classifier: Intended Audience :: Developers
Classifier: Topic :: System :: Software Distribution
Classifier: Programming Language :: Python
Classifier: Programming Language :: Python :: 3
Classifier: Programming Language :: Python :: 3.7
Classifier: Topic :: Software Development :: Libraries :: Python Modules
Classifier: License :: OSI Approved :: GNU Library or Lesser General Public License (LGPL)
Requires-Python: >=3.8
License-File: LICENSE
Requires-Dist: udata
Requires-Dist: blinker ==1.4
Requires-Dist: certifi ==2024.2.2
Requires-Dist: click ==8.1.2
Requires-Dist: feedgenerator ==2.1.0
Requires-Dist: feedparser ==6.0.8
Requires-Dist: flask ==2.1.2
Requires-Dist: flask-themes2 ==1.0.0
Requires-Dist: itsdangerous ==2.1.2
Requires-Dist: jinja2 ==3.1.2
Requires-Dist: markupsafe ==2.1.2
Requires-Dist: python-frontmatter ==1.0.0
Requires-Dist: pytz ==2024.1
Requires-Dist: pyyaml ==6.0.1
Requires-Dist: sentry-sdk[flask] ==1.9.0
Requires-Dist: sgmllib3k ==1.0.0
Requires-Dist: urllib3 ==1.25.11
Requires-Dist: werkzeug ==2.2.2
